fixtup_minio_s3/__init__.py
fixtup_minio_s3/main.py
fixtup_minio_s3-0.0.1a0.dist-info/LICENSE
fixtup_minio_s3-0.0.1a0.dist-info/METADATA
fixtup_minio_s3-0.0.1a0.dist-info/WHEEL
fixtup_minio_s3-0.0.1a0.dist-info/RECORD
