Metadata-Version: 2.1
Name: fixtup-minio-s3
Version: 0.0.1a0
Summary: fixtup plugin to load a fixture into a minio bucket and run s3 tests
License: MIT
Author: Fabien Arcellier
Author-email: fabien.arcellier@gmail.com
Requires-Python: >=3.10,<4.0
Classifier: Environment :: Console
Classifier: Intended Audience :: Developers
Classifier: License :: OSI Approved :: MIT License
Classifier: Operating System :: OS Independent
Classifier: Programming Language :: Python :: 3
Classifier: Programming Language :: Python :: 3.10
Classifier: Programming Language :: Python :: 3.11
Classifier: Programming Language :: Python :: 3.12
Project-URL: Chat, https://discord.gg/nMn9YPRGSY
Project-URL: Documentation, https://fixtup-minio-s3.readthedocs.io/en/latest/
Project-URL: Issue Tracker, https://github.com/FabienArcellier/fixtup-minio-s3/issues
Project-URL: Source code, https://github.com/FabienArcellier/fixtup-minio-s3
